{
    "data": [
        {
            "frame_index": 1,
            "skeleton": [
                {
                    "pose": [
                        943.6292724609375,
                        555.9155883789062,
                        946.507080078125,
                        554.477294921875,
                        978.1629028320312,
                        555.9155883789062,
                        947.9459228515625,
                        561.6685180664062,
                        991.1129760742188,
                        691.8295593261719,
                        940.7515258789062,
                        596.1864013671875,
                        996.8685913085938,
                        593.3098754882812,
                        910.53466796875,
                        639.3336791992188,
                        1029.9632568359375,
                        645.086669921875,
                        874.5621337890625,
                        656.5925903320312,
                        1040.0355224609375,
                        688.2339477539062,
                        973.84619140625,
                        695.4251708984375,
                        1008.3797607421875,
                        688.2339477539062,
                        940.7515258789062,
                        768.7755737304688,
                        1008.3797607421875,
                        732.8194580078125,
                        952.2626953125,
                        849.3171997070312,
                        1038.5966796875,
                        796.1022338867188
                    ],
                    "score": [
                        1,
                        1,
                        1,
                        1,
                        1,
                        1,
                        1,
                        1,
                        1,
                        1,
                        1,
                        1,
                        1,
                        1,
                        1,
                        1,
                        1
                    ]
                }
            ]
        },
        {
            "frame_index": 2,
            "skeleton": [
                {
                    "pose": [
                        917.5628051757812,
                        575.4602661132812,
                        917.5628051757812,
                        569.7108154296875,
                        972.1477661132812,
                        556.7745361328125,
                        937.6729736328125,
                        562.5239868164062,
                        991.5397033691406,
                        691.1680603027344,
                        936.236572265625,
                        594.14599609375,
                        989.385009765625,
                        592.7086181640625,
                        904.6348266601562,
                        638.7042846679688,
                        1022.4232788085938,
                        640.1416625976562,
                        868.7236938476562,
                        661.7021484375,
                        1035.351318359375,
                        687.5746459960938,
                        975.0205688476562,
                        694.761474609375,
                        1008.058837890625,
                        687.5746459960938,
                        941.9823608398438,
                        768.0670166015625,
                        1000.8766479492188,
                        729.2582397460938,
                        953.4739990234375,
                        848.5594482421875,
                        1028.1690673828125,
                        798.251708984375
                    ],
                    "score": [
                        1,
                        1,
                        1,
                        1,
                        1,
                        1,
                        1,
                        1,
                        1,
                        1,
                        1,
                        1,
                        1,
                        1,
                        1,
                        1,
                        1
                    ]
                }
            ]
        },
        {
            "frame_index": 3,
            "skeleton": [
                {
                    "pose": [
                        927.7427368164062,
                        565.549072265625,
                        927.7427368164062,
                        562.6679077148438,
                        965.0259399414062,
                        556.9053955078125,
                        933.4786987304688,
                        562.6679077148438,
                        994.4223327636719,
                        693.7639770507812,
                        929.1767578125,
                        597.24267578125,
                        985.1015014648438,
                        595.8020629882812,
                        899.0633544921875,
                        643.3424072265625,
                        1013.7808837890625,
                        639.0205688476562,
                        864.6481323242188,
                        667.8328857421875,
                        1026.6866455078125,
                        686.5609130859375,
                        977.9317016601562,
                        696.6452026367188,
                        1010.9129638671875,
                        690.8827514648438,
                        940.6484985351562,
                        768.676025390625,
                        992.2713623046875,
                        731.2200317382812,
                        954.9881591796875,
                        845.0287475585938,
                        1013.7808837890625,
                        793.16650390625
                    ],
                    "score": [
                        1,
                        1,
                        1,
                        1,
                        1,
                        1,
                        1,
                        1,
                        1,
                        1,
                        1,
                        1,
                        1,
                        1,
                        1,
                        1,
                        1
                    ]
                }
            ]
        },
        {
            "frame_index": 4,
            "skeleton": [
                {
                    "pose": [
                        915.02783203125,
                        577.343505859375,
                        919.3157348632812,
                        570.1397094726562,
                        959.3358154296875,
                        562.9358520507812,
                        925.0328369140625,
                        570.1397094726562,
                        992.9241333007812,
                        695.4862670898438,
                        922.1742553710938,
                        603.2772827148438,
                        979.3458862304688,
                        598.9550170898438,
                        892.1592407226562,
                        650.822509765625,
                        1009.3609619140625,
                        645.0595092773438,
                        862.1441040039062,
                        675.3155517578125,
                        1020.7953491210938,
                        686.8416748046875,
                        976.4873046875,
                        699.8085327148438,
                        1009.3609619140625,
                        691.1640014648438,
                        937.896484375,
                        771.8468017578125,
                        989.3509521484375,
                        734.3869018554688,
                        966.4822998046875,
                        842.4442749023438,
                        1002.2145385742188,
                        802.1028442382812
                    ],
                    "score": [
                        1,
                        1,
                        1,
                        1,
                        1,
                        1,
                        1,
                        1,
                        1,
                        1,
                        1,
                        1,
                        1,
                        1,
                        1,
                        1,
                        1
                    ]
                }
            ]
        },
        {
            "frame_index": 5,
            "skeleton": [
                {
                    "pose": [
                        910.2684326171875,
                        578.6397094726562,
                        913.1363525390625,
                        572.893310546875,
                        913.1363525390625,
                        571.4566650390625,
                        917.4381713867188,
                        578.6397094726562,
                        989.1348571777344,
                        700.0325317382812,
                        916.0042114257812,
                        613.1181640625,
                        973.361572265625,
                        608.808349609375,
                        885.8914794921875,
                        659.08935546875,
                        1003.4741821289062,
                        654.7796020507812,
                        858.6467895507812,
                        682.0750122070312,
                        1009.2099609375,
                        699.3142700195312,
                        973.361572265625,
                        706.4972534179688,
                        1004.9081420898438,
                        693.5678100585938,
                        938.9471435546875,
                        778.3273315429688,
                        979.0973510742188,
                        733.792724609375,
                        980.53125,
                        842.9744873046875,
                        987.7008666992188,
                        794.1299438476562
                    ],
                    "score": [
                        1,
                        1,
                        1,
                        1,
                        1,
                        1,
                        1,
                        1,
                        1,
                        1,
                        1,
                        1,
                        1,
                        1,
                        1,
                        1,
                        1
                    ]
                }
            ]
        },
        {
            "frame_index": 6,
            "skeleton": [
                {
                    "pose": [
                        908.1781616210938,
                        579.9271240234375,
                        911.0535888671875,
                        577.05322265625,
                        912.4912109375,
                        577.05322265625,
                        916.8043212890625,
                        585.675048828125,
                        984.3759460449219,
                        708.5362243652344,
                        913.928955078125,
                        623.036376953125,
                        965.6859130859375,
                        614.4144897460938,
                        883.7373657226562,
                        661.8345947265625,
                        993.0021362304688,
                        656.0867309570312,
                        857.85888671875,
                        677.6412963867188,
                        1000.1905517578125,
                        707.8177490234375,
                        969.9989624023438,
                        715.0026245117188,
                        998.7529296875,
                        702.06982421875,
                        942.6828002929688,
                        789.7252197265625,
                        974.3120727539062,
                        737.994140625,
                        993.0021362304688,
                        852.9520263671875,
                        978.6251220703125,
                        791.1621704101562
                    ],
                    "score": [
                        1,
                        1,
                        1,
                        1,
                        1,
                        1,
                        1,
                        1,
                        1,
                        1,
                        1,
                        1,
                        1,
                        1,
                        1,
                        1,
                        1
                    ]
                }
            ]
        },
        {
            "frame_index": 7,
            "skeleton": [
                {
                    "pose": [
                        941.9011840820312,
                        591.3118286132812,
                        911.84912109375,
                        588.4364013671875,
                        940.4700927734375,
                        586.998779296875,
                        913.2801513671875,
                        595.6248779296875,
                        977.6773376464844,
                        719.2659912109375,
                        914.7113037109375,
                        628.6917114257812,
                        963.3668823242188,
                        627.2539672851562,
                        871.77978515625,
                        668.9469604492188,
                        991.98779296875,
                        673.260009765625,
                        853.17626953125,
                        673.260009765625,
                        880.3660888671875,
                        667.5092163085938,
                        963.3668823242188,
                        723.5790405273438,
                        991.98779296875,
                        714.9529418945312,
                        944.7632446289062,
                        804.0895385742188,
                        969.0910034179688,
                        748.019775390625,
                        997.7119140625,
                        860.159423828125,
                        990.5567626953125,
                        854.4086303710938
                    ],
                    "score": [
                        1,
                        1,
                        1,
                        1,
                        1,
                        1,
                        1,
                        1,
                        1,
                        1,
                        1,
                        1,
                        1,
                        1,
                        1,
                        1,
                        1
                    ]
                }
            ]
        },
        {
            "frame_index": 8,
            "skeleton": [
                {
                    "pose": [
                        904.4409790039062,
                        600.4252319335938,
                        907.3131713867188,
                        596.10791015625,
                        907.3131713867188,
                        594.6687622070312,
                        908.7492065429688,
                        600.4252319335938,
                        973.3730773925781,
                        727.7872009277344,
                        908.7492065429688,
                        633.5249633789062,
                        956.1400756835938,
                        632.0858154296875,
                        857.0501098632812,
                        665.185546875,
                        976.2452392578125,
                        655.1117553710938,
                        841.253173828125,
                        650.7943725585938,
                        986.2977905273438,
                        681.015869140625,
                        959.01220703125,
                        731.385009765625,
                        987.7339477539062,
                        724.1893920898438,
                        941.7792358398438,
                        806.2191772460938,
                        964.756591796875,
                        755.8500366210938,
                        992.0421752929688,
                        856.5882568359375,
                        966.192626953125,
                        810.5364990234375
                    ],
                    "score": [
                        1,
                        1,
                        1,
                        1,
                        1,
                        1,
                        1,
                        1,
                        1,
                        1,
                        1,
                        1,
                        1,
                        1,
                        1,
                        1,
                        1
                    ]
                }
            ]
        },
        {
            "frame_index": 9,
            "skeleton": [
                {
                    "pose": [
                        899.66943359375,
                        596.1651611328125,
                        901.1032104492188,
                        594.7271728515625,
                        928.3456420898438,
                        590.413330078125,
                        902.5370483398438,
                        600.47900390625,
                        965.6246337890625,
                        722.7052917480469,
                        903.9708251953125,
                        630.6760864257812,
                        946.9851684570312,
                        629.2381591796875,
                        850.9199829101562,
                        652.2454223632812,
                        971.35986328125,
                        668.0629272460938,
                        836.5818481445312,
                        629.2381591796875,
                        974.2274780273438,
                        708.32568359375,
                        952.7203979492188,
                        728.4570922851562,
                        978.5288696289062,
                        716.9534912109375,
                        945.55126953125,
                        807.5447387695312,
                        961.3232421875,
                        757.2162475585938,
                        992.8670043945312,
                        856.4351806640625,
                        968.4922485351562,
                        811.8585205078125
                    ],
                    "score": [
                        1,
                        1,
                        1,
                        1,
                        1,
                        1,
                        1,
                        1,
                        1,
                        1,
                        1,
                        1,
                        1,
                        1,
                        1,
                        1,
                        1
                    ]
                }
            ]
        },
        {
            "frame_index": 10,
            "skeleton": [
                {
                    "pose": [
                        923.2644653320312,
                        581.3634033203125,
                        918.9671020507812,
                        575.6116943359375,
                        918.9671020507812,
                        579.925537109375,
                        894.6156616210938,
                        594.304931640625,
                        956.9266662597656,
                        715.8110656738281,
                        893.183349609375,
                        625.9396362304688,
                        939.021240234375,
                        620.1878662109375,
                        845.9129028320312,
                        638.881103515625,
                        961.9402465820312,
                        657.5744018554688,
                        831.5885009765625,
                        608.6843872070312,
                        963.3726806640625,
                        697.8367919921875,
                        943.3185424804688,
                        720.8438720703125,
                        970.5347900390625,
                        710.7782592773438,
                        957.6428833007812,
                        807.120361328125,
                        957.6428833007812,
                        771.1718139648438,
                        994.88623046875,
                        853.134521484375,
                        969.1023559570312,
                        799.9306640625
                    ],
                    "score": [
                        1,
                        1,
                        1,
                        1,
                        1,
                        1,
                        1,
                        1,
                        1,
                        1,
                        1,
                        1,
                        1,
                        1,
                        1,
                        1,
                        1
                    ]
                }
            ]
        },
        {
            "frame_index": 11,
            "skeleton": [
                {
                    "pose": [
                        919.901123046875,
                        577.1455688476562,
                        918.4682006835938,
                        571.3843994140625,
                        918.4682006835938,
                        571.3843994140625,
                        884.0777587890625,
                        580.026123046875,
                        947.8434448242188,
                        705.3312377929688,
                        894.1082763671875,
                        611.7124633789062,
                        927.0657958984375,
                        605.9512939453125,
                        842.5225219726562,
                        624.6751098632812,
                        917.0352783203125,
                        582.90673828125,
                        826.76025390625,
                        588.6678466796875,
                        911.3035278320312,
                        555.541259765625,
                        934.2305297851562,
                        709.652099609375,
                        961.4563598632812,
                        701.0103759765625,
                        947.126953125,
                        783.1067504882812,
                        949.9927978515625,
                        780.2261962890625,
                        980.08447265625,
                        830.6362915039062,
                        961.4563598632812,
                        809.031982421875
                    ],
                    "score": [
                        1,
                        1,
                        1,
                        1,
                        1,
                        1,
                        1,
                        1,
                        1,
                        1,
                        1,
                        1,
                        1,
                        1,
                        1,
                        1,
                        1
                    ]
                }
            ]
        },
        {
            "frame_index": 12,
            "skeleton": [
                {
                    "pose": [
                        870.2069091796875,
                        566.571533203125,
                        873.0831909179688,
                        560.8252563476562,
                        870.2069091796875,
                        557.9520874023438,
                        877.3974609375,
                        568.0081176757812,
                        939.9551391601562,
                        698.0177001953125,
                        884.5880126953125,
                        603.92236328125,
                        917.66455078125,
                        585.2468872070312,
                        844.321044921875,
                        615.4149169921875,
                        910.4739990234375,
                        557.9520874023438,
                        819.8731689453125,
                        580.9371948242188,
                        865.8926391601562,
                        611.105224609375,
                        927.731201171875,
                        701.609130859375,
                        952.1790771484375,
                        694.42626953125,
                        934.9217529296875,
                        773.4376220703125,
                        933.4837036132812,
                        770.5645141601562,
                        978.06494140625,
                        823.7175903320312,
                        952.1790771484375,
                        782.05712890625
                    ],
                    "score": [
                        1,
                        1,
                        1,
                        1,
                        1,
                        1,
                        1,
                        1,
                        1,
                        1,
                        1,
                        1,
                        1,
                        1,
                        1,
                        1,
                        1
                    ]
                }
            ]
        },
        {
            "frame_index": 13,
            "skeleton": [
                {
                    "pose": [
                        862.7432250976562,
                        558.1951904296875,
                        864.1799926757812,
                        552.43212890625,
                        862.7432250976562,
                        552.43212890625,
                        867.0534057617188,
                        559.6359252929688,
                        934.5794067382812,
                        690.0247802734375,
                        881.420654296875,
                        592.7734375,
                        910.1551513671875,
                        581.2473754882812,
                        844.0658569335938,
                        607.1810302734375,
                        923.0855712890625,
                        597.0957641601562,
                        816.7681274414062,
                        579.8065795898438,
                        913.028564453125,
                        562.5174560546875,
                        924.5223388671875,
                        695.0674438476562,
                        944.636474609375,
                        684.9821166992188,
                        913.028564453125,
                        764.2239379882812,
                        924.5223388671875,
                        752.6978149414062,
                        961.8770751953125,
                        797.3614501953125,
                        961.8770751953125,
                        798.8021850585938
                    ],
                    "score": [
                        1,
                        1,
                        1,
                        1,
                        1,
                        1,
                        1,
                        1,
                        1,
                        1,
                        1,
                        1,
                        1,
                        1,
                        1,
                        1,
                        1
                    ]
                }
            ]
        },
        {
            "frame_index": 14,
            "skeleton": [
                {
                    "pose": [
                        855.3560180664062,
                        552.5418090820312,
                        856.795166015625,
                        549.6644897460938,
                        855.3560180664062,
                        546.7871704101562,
                        858.2341918945312,
                        552.5418090820312,
                        922.27197265625,
                        684.1790161132812,
                        876.9418334960938,
                        585.6309204101562,
                        894.2105102539062,
                        578.4376220703125,
                        845.28271484375,
                        602.8948364257812,
                        917.2352294921875,
                        589.9468994140625,
                        813.6235961914062,
                        584.1922607421875,
                        914.357177734375,
                        579.8763427734375,
                        918.6743774414062,
                        686.3369750976562,
                        925.8695678710938,
                        682.0210571289062,
                        901.4057006835938,
                        755.3926391601562,
                        898.5276489257812,
                        755.3926391601562,
                        960.4068603515625,
                        789.9204711914062,
                        954.6506958007812,
                        784.165771484375
                    ],
                    "score": [
                        1,
                        1,
                        1,
                        1,
                        1,
                        1,
                        1,
                        1,
                        1,
                        1,
                        1,
                        1,
                        1,
                        1,
                        1,
                        1,
                        1
                    ]
                }
            ]
        },
        {
            "frame_index": 15,
            "skeleton": [
                {
                    "pose": [
                        843.0223388671875,
                        550.89892578125,
                        847.3349609375,
                        546.5762329101562,
                        844.4598999023438,
                        546.5762329101562,
                        850.2100830078125,
                        550.89892578125,
                        907.7117309570312,
                        681.3008422851562,
                        874.6482543945312,
                        579.717041015625,
                        883.2735595703125,
                        575.3943481445312,
                        841.5847778320312,
                        602.7715454101562,
                        843.0223388671875,
                        601.3306274414062,
                        804.208740234375,
                        585.4806518554688,
                        913.4618530273438,
                        572.5125122070312,
                        914.8994140625,
                        682.0213012695312,
                        900.5240478515625,
                        680.5803833007812,
                        887.5861206054688,
                        751.1846923828125,
                        883.2735595703125,
                        746.8619995117188,
                        953.7130737304688,
                        775.6801147460938,
                        939.337646484375,
                        767.03466796875
                    ],
                    "score": [
                        1,
                        1,
                        1,
                        1,
                        1,
                        1,
                        1,
                        1,
                        1,
                        1,
                        1,
                        1,
                        1,
                        1,
                        1,
                        1,
                        1
                    ]
                }
            ]
        },
        {
            "frame_index": 16,
            "skeleton": [
                {
                    "pose": [
                        835.62939453125,
                        553.151611328125,
                        837.0603637695312,
                        547.40380859375,
                        835.62939453125,
                        547.40380859375,
                        842.7839965820312,
                        551.7146606445312,
                        900.0206909179688,
                        676.7291870117188,
                        868.5404663085938,
                        579.0166625976562,
                        872.833251953125,
                        573.2688598632812,
                        844.2149658203125,
                        603.44482421875,
                        847.0767822265625,
                        604.8817749023438,
                        798.4255981445312,
                        587.6383666992188,
                        878.556884765625,
                        685.3508911132812,
                        908.606201171875,
                        679.6030883789062,
                        891.4351806640625,
                        673.8552856445312,
                        882.8496704101562,
                        752.8873901367188,
                        878.556884765625,
                        741.3919067382812,
                        940.0863647460938,
                        783.0634155273438,
                        942.9481811523438,
                        784.5003051757812
                    ],
                    "score": [
                        1,
                        1,
                        1,
                        1,
                        1,
                        1,
                        1,
                        1,
                        1,
                        1,
                        1,
                        1,
                        1,
                        1,
                        1,
                        1,
                        1
                    ]
                }
            ]
        },
        {
            "frame_index": 17,
            "skeleton": [
                {
                    "pose": [
                        824.8314819335938,
                        555.33349609375,
                        827.6931762695312,
                        549.5855712890625,
                        826.2623291015625,
                        551.0225830078125,
                        830.554931640625,
                        553.8965454101562,
                        892.7980346679688,
                        676.0390014648438,
                        859.1724853515625,
                        578.3250122070312,
                        853.448974609375,
                        578.3250122070312,
                        840.571044921875,
                        601.3165283203125,
                        842.001953125,
                        604.1904907226562,
                        794.7830200195312,
                        594.1316528320312,
                        869.1886596679688,
                        681.786865234375,
                        900.6678466796875,
                        680.3499145507812,
                        884.92822265625,
                        671.7280883789062,
                        879.2047729492188,
                        753.6353759765625,
                        834.8475952148438,
                        704.7783813476562,
                        943.5941772460938,
                        788.1226196289062,
                        899.2369995117188,
                        752.198486328125
                    ],
                    "score": [
                        1,
                        1,
                        1,
                        1,
                        1,
                        1,
                        1,
                        1,
                        1,
                        1,
                        1,
                        1,
                        1,
                        1,
                        1,
                        1,
                        1
                    ]
                }
            ]
        },
        {
            "frame_index": 18,
            "skeleton": [
                {
                    "pose": [
                        813.8548583984375,
                        554.0092163085938,
                        815.2935791015625,
                        548.2549438476562,
                        813.8548583984375,
                        548.2549438476562,
                        819.6094360351562,
                        552.5706176757812,
                        882.1906433105469,
                        672.6904602050781,
                        846.9437866210938,
                        574.1490478515625,
                        845.5051879882812,
                        574.1490478515625,
                        835.4345703125,
                        601.481689453125,
                        838.3118896484375,
                        605.79736328125,
                        796.5911254882812,
                        601.481689453125,
                        802.345703125,
                        604.3588256835938,
                        891.5418090820312,
                        679.1640014648438,
                        872.8394775390625,
                        666.2169189453125,
                        878.5940551757812,
                        753.9691772460938,
                        826.802734375,
                        694.9881591796875,
                        943.3331909179688,
                        789.9332275390625,
                        867.0848999023438,
                        732.3907470703125
                    ],
                    "score": [
                        1,
                        1,
                        1,
                        1,
                        1,
                        1,
                        1,
                        1,
                        1,
                        1,
                        1,
                        1,
                        1,
                        1,
                        1,
                        1,
                        1
                    ]
                }
            ]
        },
        {
            "frame_index": 19,
            "skeleton": [
                {
                    "pose": [
                        801.0599975585938,
                        557.6882934570312,
                        802.4902954101562,
                        549.0548095703125,
                        802.4902954101562,
                        551.9326171875,
                        808.211669921875,
                        553.3715209960938,
                        866.1401977539062,
                        672.802001953125,
                        835.3880004882812,
                        574.955322265625,
                        832.52734375,
                        574.955322265625,
                        832.52734375,
                        603.7337646484375,
                        828.236328125,
                        602.2948608398438,
                        793.9082641601562,
                        608.0505981445312,
                        793.9082641601562,
                        608.0505981445312,
                        876.8677368164062,
                        678.5576782226562,
                        855.4126586914062,
                        667.0463256835938,
                        872.5767211914062,
                        753.3815307617188,
                        819.654296875,
                        688.630126953125,
                        939.8024291992188,
                        786.476806640625,
                        831.0969848632812,
                        731.7977905273438
                    ],
                    "score": [
                        1,
                        1,
                        1,
                        1,
                        1,
                        1,
                        1,
                        1,
                        1,
                        1,
                        1,
                        1,
                        1,
                        1,
                        1,
                        1,
                        1
                    ]
                }
            ]
        },
        {
            "frame_index": 20,
            "skeleton": [
                {
                    "pose": [
                        786.6791381835938,
                        555.038330078125,
                        788.1192626953125,
                        547.8314208984375,
                        786.6791381835938,
                        549.2728271484375,
                        793.8795166015625,
                        553.5969848632812,
                        857.9630432128906,
                        666.7459106445312,
                        821.2410278320312,
                        575.2177734375,
                        825.5612182617188,
                        573.7763671875,
                        828.44140625,
                        606.9283447265625,
                        825.5612182617188,
                        605.4869384765625,
                        801.0799560546875,
                        621.3422241210938,
                        785.2390747070312,
                        599.721435546875,
                        865.8834838867188,
                        670.349365234375,
                        850.0426025390625,
                        663.1424560546875,
                        867.3235473632812,
                        748.184326171875,
                        814.0406494140625,
                        689.08740234375,
                        930.68701171875,
                        781.3362426757812,
                        799.6398315429688,
                        728.0048828125
                    ],
                    "score": [
                        1,
                        1,
                        1,
                        1,
                        1,
                        1,
                        1,
                        1,
                        1,
                        1,
                        1,
                        1,
                        1,
                        1,
                        1,
                        1,
                        1
                    ]
                }
            ]
        },
        {
            "frame_index": 21,
            "skeleton": [
                {
                    "pose": [
                        775.557861328125,
                        557.0567016601562,
                        776.9962158203125,
                        551.30029296875,
                        775.557861328125,
                        551.30029296875,
                        782.7494506835938,
                        554.1785278320312,
                        842.4394226074219,
                        669.305908203125,
                        810.0773315429688,
                        577.2039794921875,
                        817.2689819335938,
                        575.764892578125,
                        824.4605712890625,
                        613.1812744140625,
                        821.5838623046875,
                        614.620361328125,
                        804.3241577148438,
                        630.4503784179688,
                        771.242919921875,
                        594.4730834960938,
                        850.35009765625,
                        672.18408203125,
                        834.5287475585938,
                        666.427734375,
                        861.8566284179688,
                        747.0169067382812,
                        798.5709228515625,
                        696.648681640625,
                        925.1424560546875,
                        781.5551147460938,
                        784.1878051757812,
                        729.747802734375
                    ],
                    "score": [
                        1,
                        1,
                        1,
                        1,
                        1,
                        1,
                        1,
                        1,
                        1,
                        1,
                        1,
                        1,
                        1,
                        1,
                        1,
                        1,
                        1
                    ]
                }
            ]
        },
        {
            "frame_index": 22,
            "skeleton": [
                {
                    "pose": [
                        764.9036254882812,
                        561.4944458007812,
                        766.3412475585938,
                        554.3009643554688,
                        763.4660034179688,
                        554.3009643554688,
                        774.9669799804688,
                        555.7396240234375,
                        827.4402770996094,
                        661.484130859375,
                        796.5313110351562,
                        580.1975708007812,
                        802.2818603515625,
                        574.4427490234375,
                        818.095703125,
                        610.4102783203125,
                        769.2164306640625,
                        584.5136108398438,
                        809.469970703125,
                        633.429443359375,
                        749.0897216796875,
                        590.2684936523438,
                        833.9096069335938,
                        662.2034912109375,
                        820.970947265625,
                        660.7647705078125,
                        852.5986328125,
                        747.0867919921875,
                        787.9056396484375,
                        688.10009765625,
                        912.9788818359375,
                        780.1768798828125,
                        774.9669799804688,
                        732.6998901367188
                    ],
                    "score": [
                        1,
                        1,
                        1,
                        1,
                        1,
                        1,
                        1,
                        1,
                        1,
                        1,
                        1,
                        1,
                        1,
                        1,
                        1,
                        1,
                        1
                    ]
                }
            ]
        },
        {
            "frame_index": 23,
            "skeleton": [
                {
                    "pose": [
                        752.9412231445312,
                        567.896240234375,
                        755.8028564453125,
                        562.1347045898438,
                        755.8028564453125,
                        562.1347045898438,
                        762.9569702148438,
                        565.0154418945312,
                        828.7749938964844,
                        668.7227172851562,
                        788.7118530273438,
                        590.9422607421875,
                        793.0042724609375,
                        583.7404174804688,
                        807.3125610351562,
                        647.1170654296875,
                        762.9569702148438,
                        580.859619140625,
                        795.8660278320312,
                        678.8053588867188,
                        738.6328735351562,
                        576.5384521484375,
                        824.4825439453125,
                        675.9246215820312,
                        833.0674438476562,
                        661.5208129882812,
                        840.2216186523438,
                        750.8243408203125,
                        770.1110229492188,
                        683.12646484375,
                        898.885498046875,
                        772.429931640625,
                        767.2493896484375,
                        732.099365234375
                    ],
                    "score": [
                        1,
                        1,
                        1,
                        1,
                        1,
                        1,
                        1,
                        1,
                        1,
                        1,
                        1,
                        1,
                        1,
                        1,
                        1,
                        1,
                        1
                    ]
                }
            ]
        },
        {
            "frame_index": 24,
            "skeleton": [
                {
                    "pose": [
                        739.4989013671875,
                        575.5704956054688,
                        743.8108520507812,
                        568.3793334960938,
                        743.8108520507812,
                        566.9411010742188,
                        750.9974365234375,
                        571.2557983398438,
                        822.8631286621094,
                        669.7744445800781,
                        773.9945068359375,
                        598.5821533203125,
                        781.1810302734375,
                        589.9527587890625,
                        795.55419921875,
                        640.290771484375,
                        753.8720703125,
                        585.6381225585938,
                        788.3676147460938,
                        680.5611572265625,
                        729.437744140625,
                        571.2557983398438,
                        815.6765747070312,
                        676.2464599609375,
                        830.0496826171875,
                        663.3024291992188,
                        828.6124267578125,
                        756.7872314453125,
                        763.9332275390625,
                        676.2464599609375,
                        888.9796142578125,
                        769.7313232421875,
                        766.8079223632812,
                        730.8991088867188
                    ],
                    "score": [
                        1,
                        1,
                        1,
                        1,
                        1,
                        1,
                        1,
                        1,
                        1,
                        1,
                        1,
                        1,
                        1,
                        1,
                        1,
                        1,
                        1
                    ]
                }
            ]
        },
        {
            "frame_index": 25,
            "skeleton": [
                {
                    "pose": [
                        731.7261962890625,
                        581.0763549804688,
                        734.588134765625,
                        573.8984375,
                        733.1571655273438,
                        573.8984375,
                        738.8811645507812,
                        576.7696533203125,
                        817.5858764648438,
                        673.6710510253906,
                        763.2080688476562,
                        602.6099853515625,
                        773.2249755859375,
                        589.6898193359375,
                        787.5349731445312,
                        651.4196166992188,
                        740.3121337890625,
                        588.2542114257812,
                        780.3800048828125,
                        674.3888549804688,
                        720.2782592773438,
                        578.2052001953125,
                        810.430908203125,
                        681.5667114257812,
                        824.7408447265625,
                        665.775390625,
                        813.2929077148438,
                        759.087890625,
                        758.9151000976562,
                        672.9533081054688,
                        874.82568359375,
                        761.958984375,
                        766.070068359375,
                        731.8118896484375
                    ],
                    "score": [
                        1,
                        1,
                        1,
                        1,
                        1,
                        1,
                        1,
                        1,
                        1,
                        1,
                        1,
                        1,
                        1,
                        1,
                        1,
                        1,
                        1
                    ]
                }
            ]
        },
        {
            "frame_index": 26,
            "skeleton": [
                {
                    "pose": [
                        729.1410522460938,
                        579.488037109375,
                        730.5726928710938,
                        573.7454223632812,
                        730.5726928710938,
                        573.7454223632812,
                        736.2991333007812,
                        576.61669921875,
                        816.4696044921875,
                        670.651611328125,
                        753.478515625,
                        599.5870361328125,
                        767.7946166992188,
                        588.1018676757812,
                        777.8159790039062,
                        641.2208862304688,
                        780.67919921875,
                        642.6565551757812,
                        790.7005615234375,
                        685.7259521484375,
                        764.931396484375,
                        662.7555541992188,
                        810.7431030273438,
                        678.5476684570312,
                        822.1961059570312,
                        662.7555541992188,
                        803.5850830078125,
                        758.9439086914062,
                        754.91015625,
                        671.3695068359375,
                        860.8496704101562,
                        757.5083618164062,
                        766.3630981445312,
                        733.102294921875
                    ],
                    "score": [
                        1,
                        1,
                        1,
                        1,
                        1,
                        1,
                        1,
                        1,
                        1,
                        1,
                        1,
                        1,
                        1,
                        1,
                        1,
                        1,
                        1
                    ]
                }
            ]
        },
        {
            "frame_index": 27,
            "skeleton": [
                {
                    "pose": [
                        722.3733520507812,
                        572.6444091796875,
                        722.3733520507812,
                        566.8903198242188,
                        722.3733520507812,
                        565.4517822265625,
                        728.1245727539062,
                        572.6444091796875,
                        811.5170593261719,
                        666.1486511230469,
                        746.8159790039062,
                        598.5379028320312,
                        764.069580078125,
                        585.5911865234375,
                        765.5074462890625,
                        631.6240234375,
                        766.9452514648438,
                        625.869873046875,
                        774.1342163085938,
                        660.39453125,
                        738.189208984375,
                        614.3616943359375,
                        802.8902587890625,
                        671.9027709960938,
                        820.1438598632812,
                        660.39453125,
                        794.263427734375,
                        758.2144165039062,
                        755.4428100585938,
                        670.4642333984375,
                        765.5074462890625,
                        730.8823852539062,
                        765.5074462890625,
                        730.8823852539062
                    ],
                    "score": [
                        1,
                        1,
                        1,
                        1,
                        1,
                        1,
                        1,
                        1,
                        1,
                        1,
                        1,
                        1,
                        1,
                        1,
                        1,
                        1,
                        1
                    ]
                }
            ]
        },
        {
            "frame_index": 28,
            "skeleton": [
                {
                    "pose": [
                        718.8128662109375,
                        567.2984619140625,
                        718.8128662109375,
                        562.98974609375,
                        718.8128662109375,
                        562.98974609375,
                        725.9708251953125,
                        567.2984619140625,
                        807.5717468261719,
                        662.0914001464844,
                        741.7183837890625,
                        593.1510620117188,
                        760.3291015625,
                        580.2247924804688,
                        756.0343017578125,
                        621.876220703125,
                        788.9609985351562,
                        608.949951171875,
                        770.3502807617188,
                        652.03759765625,
                        767.4871215820312,
                        654.9100952148438,
                        798.982177734375,
                        667.83642578125,
                        816.1613159179688,
                        656.3463745117188,
                        790.3926391601562,
                        755.4480590820312,
                        754.6027221679688,
                        670.7089233398438,
                        861.972412109375,
                        748.2667846679688,
                        861.972412109375,
                        748.2667846679688
                    ],
                    "score": [
                        1,
                        1,
                        1,
                        1,
                        1,
                        1,
                        1,
                        1,
                        1,
                        1,
                        1,
                        1,
                        1,
                        1,
                        1,
                        1,
                        1
                    ]
                }
            ]
        },
        {
            "frame_index": 29,
            "skeleton": [
                {
                    "pose": [
                        723.1551513671875,
                        557.2091064453125,
                        723.1551513671875,
                        552.9083251953125,
                        744.5844116210938,
                        544.306640625,
                        723.1551513671875,
                        557.2091064453125,
                        801.7288513183594,
                        656.1280517578125,
                        738.869873046875,
                        587.3148803710938,
                        763.1563110351562,
                        574.4124145507812,
                        757.44189453125,
                        617.420654296875,
                        786.0140991210938,
                        608.8190307617188,
                        771.72802734375,
                        648.9600219726562,
                        770.2993774414062,
                        648.9600219726562,
                        791.7285766601562,
                        660.4288940429688,
                        811.7291259765625,
                        651.8272094726562,
                        791.7285766601562,
                        752.1798095703125,
                        756.0133056640625,
                        670.4641723632812,
                        861.7305908203125,
                        747.8789672851562,
                        764.5849609375,
                        733.5429077148438
                    ],
                    "score": [
                        1,
                        1,
                        1,
                        1,
                        1,
                        1,
                        1,
                        1,
                        1,
                        1,
                        1,
                        1,
                        1,
                        1,
                        1,
                        1,
                        1
                    ]
                }
            ]
        },
        {
            "frame_index": 30,
            "skeleton": [
                {
                    "pose": [
                        721.6717529296875,
                        547.5101928710938,
                        721.6717529296875,
                        543.2009887695312,
                        721.6717529296875,
                        541.7646484375,
                        721.6717529296875,
                        547.5101928710938,
                        797.9123229980469,
                        652.3668212890625,
                        738.9337158203125,
                        577.6744384765625,
                        767.7037353515625,
                        569.0560913085938,
                        759.07275390625,
                        609.2750854492188,
                        787.8427734375,
                        606.4022827148438,
                        773.4578247070312,
                        655.2396240234375,
                        767.7037353515625,
                        659.5487670898438,
                        790.7197875976562,
                        659.5487670898438,
                        805.1048583984375,
                        645.1848754882812,
                        793.5968017578125,
                        744.2958984375,
                        754.7572631835938,
                        672.476318359375,
                        866.9603271484375,
                        745.7323608398438,
                        764.8267822265625,
                        729.9320068359375
                    ],
                    "score": [
                        1,
                        1,
                        1,
                        1,
                        1,
                        1,
                        1,
                        1,
                        1,
                        1,
                        1,
                        1,
                        1,
                        1,
                        1,
                        1,
                        1
                    ]
                }
            ]
        },
        {
            "frame_index": 31,
            "skeleton": [
                {
                    "pose": [
                        755.19287109375,
                        531.11376953125,
                        725.1692504882812,
                        533.9926147460938,
                        753.76318359375,
                        529.6742553710938,
                        726.5989379882812,
                        538.3109130859375,
                        793.7947082519531,
                        648.427978515625,
                        738.0364990234375,
                        567.0997314453125,
                        768.0601196289062,
                        559.9025268554688,
                        759.4819946289062,
                        591.5701293945312,
                        799.5134887695312,
                        605.9645385742188,
                        759.4819946289062,
                        624.67724609375,
                        769.4898681640625,
                        659.2237548828125,
                        785.216552734375,
                        652.0265502929688,
                        802.3728637695312,
                        644.8294067382812,
                        792.364990234375,
                        736.9534912109375,
                        756.6226196289062,
                        675.0576171875,
                        860.9905395507812,
                        745.5901489257812,
                        763.7710571289062,
                        726.87744140625
                    ],
                    "score": [
                        1,
                        1,
                        1,
                        1,
                        1,
                        1,
                        1,
                        1,
                        1,
                        1,
                        1,
                        1,
                        1,
                        1,
                        1,
                        1,
                        1
                    ]
                }
            ]
        },
        {
            "frame_index": 32,
            "skeleton": [
                {
                    "pose": [
                        725.7344970703125,
                        534.5678100585938,
                        725.7344970703125,
                        528.8076782226562,
                        753.0107421875,
                        520.16748046875,
                        728.6056518554688,
                        533.1277465820312,
                        788.900634765625,
                        639.6897277832031,
                        738.65478515625,
                        559.0482177734375,
                        777.4158935546875,
                        556.1681518554688,
                        758.7531127929688,
                        589.288818359375,
                        804.6921997070312,
                        602.2490234375,
                        758.7531127929688,
                        625.2894897460938,
                        808.9989013671875,
                        641.1297607421875,
                        780.2870483398438,
                        644.0098266601562,
                        797.5142211914062,
                        635.36962890625,
                        787.4650268554688,
                        731.8514404296875,
                        761.6243286132812,
                        672.8103637695312,
                        856.37353515625,
                        746.2517700195312,
                        758.7531127929688,
                        727.5313720703125
                    ],
                    "score": [
                        1,
                        1,
                        1,
                        1,
                        1,
                        1,
                        1,
                        1,
                        1,
                        1,
                        1,
                        1,
                        1,
                        1,
                        1,
                        1,
                        1
                    ]
                }
            ]
        },
        {
            "frame_index": 33,
            "skeleton": [
                {
                    "pose": [
                        725.6473999023438,
                        532.29833984375,
                        725.6473999023438,
                        527.9779052734375,
                        758.4920043945312,
                        523.6575317382812,
                        728.5034790039062,
                        530.8582153320312,
                        791.3365173339844,
                        639.5882568359375,
                        738.4996337890625,
                        558.220703125,
                        775.6282958984375,
                        553.9003295898438,
                        755.6358642578125,
                        587.0233764648438,
                        809.9008178710938,
                        602.8648681640625,
                        755.6358642578125,
                        624.4668579101562,
                        809.9008178710938,
                        634.5478515625,
                        781.34033203125,
                        641.7484741210938,
                        801.3327026367188,
                        637.4280395507812,
                        781.34033203125,
                        726.7163696289062,
                        765.632080078125,
                        680.632080078125,
                        848.4574584960938,
                        745.4381103515625,
                        759.9199829101562,
                        732.4769287109375
                    ],
                    "score": [
                        1,
                        1,
                        1,
                        1,
                        1,
                        1,
                        1,
                        1,
                        1,
                        1,
                        1,
                        1,
                        1,
                        1,
                        1,
                        1,
                        1
                    ]
                }
            ]
        },
        {
            "frame_index": 34,
            "skeleton": [
                {
                    "pose": [
                        725.4411010742188,
                        533.0800170898438,
                        726.86962890625,
                        528.7630615234375,
                        728.2982177734375,
                        528.7630615234375,
                        728.2982177734375,
                        533.0800170898438,
                        794.72607421875,
                        639.5638427734375,
                        739.7266845703125,
                        560.4204711914062,
                        779.7262573242188,
                        556.1035766601562,
                        755.4407958984375,
                        594.9557495117188,
                        812.5830078125,
                        603.589599609375,
                        749.7265625,
                        635.2469482421875,
                        806.8688354492188,
                        633.8079833984375,
                        782.5833129882812,
                        639.5638427734375,
                        806.8688354492188,
                        639.5638427734375,
                        768.2977905273438,
                        727.341064453125,
                        765.440673828125,
                        688.4888916015625,
                        825.4400024414062,
                        741.7307739257812,
                        758.2979125976562,
                        744.6087646484375
                    ],
                    "score": [
                        1,
                        1,
                        1,
                        1,
                        1,
                        1,
                        1,
                        1,
                        1,
                        1,
                        1,
                        1,
                        1,
                        1,
                        1,
                        1,
                        1
                    ]
                }
            ]
        },
        {
            "frame_index": 35,
            "skeleton": [
                {
                    "pose": [
                        727.0674438476562,
                        536.7821044921875,
                        727.0674438476562,
                        531.038818359375,
                        727.0674438476562,
                        531.038818359375,
                        729.9303588867188,
                        535.3462524414062,
                        797.9238586425781,
                        647.3408203125,
                        738.5189819335938,
                        566.9345092773438,
                        782.8937377929688,
                        558.3195190429688,
                        754.264892578125,
                        601.3943481445312,
                        811.5225219726562,
                        605.7018432617188,
                        741.3818359375,
                        643.0333251953125,
                        754.264892578125,
                        631.5466918945312,
                        784.3251953125,
                        647.3408203125,
                        811.5225219726562,
                        647.3408203125,
                        762.853515625,
                        697.5947875976562,
                        788.6194458007812,
                        678.9290161132812,
                        762.853515625,
                        750.720458984375,
                        768.5792846679688,
                        724.87548828125
                    ],
                    "score": [
                        1,
                        1,
                        1,
                        1,
                        1,
                        1,
                        1,
                        1,
                        1,
                        1,
                        1,
                        1,
                        1,
                        1,
                        1,
                        1,
                        1
                    ]
                }
            ]
        },
        {
            "frame_index": 36,
            "skeleton": [
                {
                    "pose": [
                        729.1610107421875,
                        541.6533813476562,
                        729.1610107421875,
                        537.3480224609375,
                        729.1610107421875,
                        537.3480224609375,
                        732.037353515625,
                        540.21826171875,
                        798.9124145507812,
                        652.1582336425781,
                        740.6663818359375,
                        571.7910766601562,
                        783.8116455078125,
                        563.1802978515625,
                        749.2954711914062,
                        614.8448486328125,
                        812.5750122070312,
                        611.9746704101562,
                        733.4755249023438,
                        663.6392822265625,
                        765.1153564453125,
                        662.2041015625,
                        783.8116455078125,
                        653.5933837890625,
                        814.01318359375,
                        650.7230834960938,
                        755.048095703125,
                        723.9146728515625,
                        765.1153564453125,
                        713.8687133789062,
                        760.8008422851562,
                        764.0982055664062,
                        759.3626708984375,
                        765.5333251953125
                    ],
                    "score": [
                        1,
                        1,
                        1,
                        1,
                        1,
                        1,
                        1,
                        1,
                        1,
                        1,
                        1,
                        1,
                        1,
                        1,
                        1,
                        1,
                        1
                    ]
                }
            ]
        },
        {
            "frame_index": 37,
            "skeleton": [
                {
                    "pose": [
                        731.4906005859375,
                        543.5648803710938,
                        732.9191284179688,
                        539.2474975585938,
                        732.9191284179688,
                        539.2474975585938,
                        735.7760009765625,
                        543.5648803710938,
                        800.7711791992188,
                        657.25634765625,
                        741.4898681640625,
                        575.2257690429688,
                        785.7723388671875,
                        565.15185546875,
                        745.7752685546875,
                        624.1563110351562,
                        817.1985473632812,
                        612.6432495117188,
                        728.6336669921875,
                        668.7694091796875,
                        802.9138793945312,
                        642.8650512695312,
                        787.2007446289062,
                        661.57373046875,
                        814.3416137695312,
                        652.93896484375,
                        750.0606689453125,
                        736.4086303710938,
                        778.6299438476562,
                        698.9912109375,
                        798.6284790039062,
                        765.1912841796875,
                        808.6277465820312,
                        772.386962890625
                    ],
                    "score": [
                        1,
                        1,
                        1,
                        1,
                        1,
                        1,
                        1,
                        1,
                        1,
                        1,
                        1,
                        1,
                        1,
                        1,
                        1,
                        1,
                        1
                    ]
                }
            ]
        },
        {
            "frame_index": 38,
            "skeleton": [
                {
                    "pose": [
                        736.1513061523438,
                        542.7659912109375,
                        739.0315551757812,
                        538.4449462890625,
                        737.5914916992188,
                        537.0045776367188,
                        740.4716796875,
                        544.2063598632812,
                        800.9569396972656,
                        665.9170532226562,
                        743.3519287109375,
                        580.2154541015625,
                        789.4359130859375,
                        568.6925048828125,
                        744.7920532226562,
                        632.0685424804688,
                        822.558837890625,
                        614.7841186523438,
                        721.7500610351562,
                        672.398681640625,
                        805.27734375,
                        642.1510620117188,
                        786.5557250976562,
                        668.0775756835938,
                        815.358154296875,
                        663.7565307617188,
                        749.1124267578125,
                        740.0957641601562,
                        772.1544189453125,
                        705.5270385742188,
                        792.3162231445312,
                        786.1873168945312,
                        796.6365966796875,
                        789.068115234375
                    ],
                    "score": [
                        1,
                        1,
                        1,
                        1,
                        1,
                        1,
                        1,
                        1,
                        1,
                        1,
                        1,
                        1,
                        1,
                        1,
                        1,
                        1,
                        1
                    ]
                }
            ]
        },
        {
            "frame_index": 39,
            "skeleton": [
                {
                    "pose": [
                        738.4933471679688,
                        542.7210083007812,
                        741.3457641601562,
                        541.2817993164062,
                        771.296630859375,
                        535.525146484375,
                        742.77197265625,
                        547.0384521484375,
                        803.3867492675781,
                        667.9286804199219,
                        744.1983032226562,
                        584.4568481445312,
                        795.54248046875,
                        570.065185546875,
                        742.77197265625,
                        631.949462890625,
                        829.77197265625,
                        614.679443359375,
                        714.2474365234375,
                        676.5636596679688,
                        808.3785400390625,
                        643.4627685546875,
                        789.8375854492188,
                        670.8070068359375,
                        816.9359130859375,
                        665.0503540039062,
                        752.755615234375,
                        742.7654418945312,
                        759.8868408203125,
                        739.8871459960938,
                        788.411376953125,
                        804.6497192382812,
                        758.4605102539062,
                        761.4746704101562
                    ],
                    "score": [
                        1,
                        1,
                        1,
                        1,
                        1,
                        1,
                        1,
                        1,
                        1,
                        1,
                        1,
                        1,
                        1,
                        1,
                        1,
                        1,
                        1
                    ]
                }
            ]
        },
        {
            "frame_index": 40,
            "skeleton": [
                {
                    "pose": [
                        744.8673095703125,
                        544.1275024414062,
                        744.8673095703125,
                        542.6868286132812,
                        779.22705078125,
                        538.36474609375,
                        747.7305908203125,
                        547.0089111328125,
                        804.2810974121094,
                        668.747802734375,
                        744.8673095703125,
                        584.467041015625,
                        802.133544921875,
                        572.9414672851562,
                        739.1406860351562,
                        636.3320922851562,
                        835.061767578125,
                        617.60302734375,
                        713.3709106445312,
                        669.4681396484375,
                        817.8818969726562,
                        647.8577270507812,
                        789.2487182617188,
                        669.4681396484375,
                        819.3134765625,
                        668.0274658203125,
                        757.7523193359375,
                        747.2658081054688,
                        783.5220947265625,
                        711.2483520507812,
                        789.2487182617188,
                        812.0971069335938,
                        766.3422241210938,
                        750.1471557617188
                    ],
                    "score": [
                        1,
                        1,
                        1,
                        1,
                        1,
                        1,
                        1,
                        1,
                        1,
                        1,
                        1,
                        1,
                        1,
                        1,
                        1,
                        1,
                        1
                    ]
                }
            ]
        },
        {
            "frame_index": 41,
            "skeleton": [
                {
                    "pose": [
                        750.0567626953125,
                        546.2457275390625,
                        751.4917602539062,
                        541.9273071289062,
                        783.0615234375,
                        536.1695556640625,
                        752.9267578125,
                        547.6851196289062,
                        808.1737976074219,
                        672.9173278808594,
                        747.186767578125,
                        585.11083984375,
                        807.456298828125,
                        575.03466796875,
                        737.1419067382812,
                        635.4916381835938,
                        841.89599609375,
                        618.2182006835938,
                        711.3121337890625,
                        662.8411865234375,
                        828.9811401367188,
                        651.3255615234375,
                        791.6714477539062,
                        674.3568115234375,
                        824.6761474609375,
                        671.4778442382812,
                        758.666748046875,
                        749.208251953125,
                        794.5414428710938,
                        700.2669067382812,
                        791.6714477539062,
                        816.8623046875,
                        785.9314575195312,
                        742.0109252929688
                    ],
                    "score": [
                        1,
                        1,
                        1,
                        1,
                        1,
                        1,
                        1,
                        1,
                        1,
                        1,
                        1,
                        1,
                        1,
                        1,
                        1,
                        1,
                        1
                    ]
                }
            ]
        },
        {
            "frame_index": 42,
            "skeleton": [
                {
                    "pose": [
                        788.4013671875,
                        542.1303100585938,
                        785.5347900390625,
                        534.9328002929688,
                        786.9681396484375,
                        539.2512817382812,
                        758.3024291992188,
                        546.4487915039062,
                        811.3338317871094,
                        676.0036926269531,
                        749.7027587890625,
                        585.3153076171875,
                        809.9005737304688,
                        573.7992553710938,
                        738.2365112304688,
                        632.8187255859375,
                        845.7326049804688,
                        619.86328125,
                        711.004150390625,
                        657.2902221679688,
                        835.6996459960938,
                        654.4112548828125,
                        794.1344604492188,
                        678.8826904296875,
                        828.533203125,
                        673.1246948242188,
                        761.1690063476562,
                        747.9786376953125,
                        782.668212890625,
                        753.736572265625,
                        789.8345947265625,
                        817.0745849609375,
                        785.5347900390625,
                        752.297119140625
                    ],
                    "score": [
                        1,
                        1,
                        1,
                        1,
                        1,
                        1,
                        1,
                        1,
                        1,
                        1,
                        1,
                        1,
                        1,
                        1,
                        1,
                        1,
                        1
                    ]
                }
            ]
        },
        {
            "frame_index": 43,
            "skeleton": [
                {
                    "pose": [
                        796.7804565429688,
                        541.0987548828125,
                        765.3024291992188,
                        542.5399780273438,
                        793.9188232421875,
                        536.7750854492188,
                        765.3024291992188,
                        546.8637084960938,
                        815.3811950683594,
                        675.8544006347656,
                        756.7174682617188,
                        581.4534301757812,
                        818.2428588867188,
                        575.6884765625,
                        739.547607421875,
                        629.0142211914062,
                        854.013427734375,
                        618.925537109375,
                        712.3619995117188,
                        656.397705078125,
                        845.4285278320312,
                        657.8389892578125,
                        796.7804565429688,
                        676.5750122070312,
                        833.98193359375,
                        675.1337890625,
                        765.3024291992188,
                        741.4306640625,
                        815.3812255859375,
                        711.1646728515625,
                        789.6264038085938,
                        814.9337158203125,
                        809.6578979492188,
                        771.6966552734375
                    ],
                    "score": [
                        1,
                        1,
                        1,
                        1,
                        1,
                        1,
                        1,
                        1,
                        1,
                        1,
                        1,
                        1,
                        1,
                        1,
                        1,
                        1,
                        1
                    ]
                }
            ]
        }
    ],
    "label": 3,
    "label_index": 3
}